endex_factset_ownership/__init__.py
endex_factset_ownership/_base_client.py
endex_factset_ownership/_client.py
endex_factset_ownership/_compat.py
endex_factset_ownership/_constants.py
endex_factset_ownership/_exceptions.py
endex_factset_ownership/_files.py
endex_factset_ownership/_models.py
endex_factset_ownership/_qs.py
endex_factset_ownership/_resource.py
endex_factset_ownership/_response.py
endex_factset_ownership/_streaming.py
endex_factset_ownership/_types.py
endex_factset_ownership/_version.py
endex_factset_ownership/py.typed
endex_factset_ownership/_utils/__init__.py
endex_factset_ownership/_utils/_logs.py
endex_factset_ownership/_utils/_proxy.py
endex_factset_ownership/_utils/_reflection.py
endex_factset_ownership/_utils/_streams.py
endex_factset_ownership/_utils/_sync.py
endex_factset_ownership/_utils/_transform.py
endex_factset_ownership/_utils/_typing.py
endex_factset_ownership/_utils/_utils.py
endex_factset_ownership/lib/.keep
endex_factset_ownership/resources/__init__.py
endex_factset_ownership/resources/factset_ownership/__init__.py
endex_factset_ownership/resources/factset_ownership/factset_ownership.py
endex_factset_ownership/resources/factset_ownership/v1/__init__.py
endex_factset_ownership/resources/factset_ownership/v1/fund_holdings.py
endex_factset_ownership/resources/factset_ownership/v1/security_holders.py
endex_factset_ownership/resources/factset_ownership/v1/v1.py
endex_factset_ownership/types/__init__.py
endex_factset_ownership/types/factset_ownership/__init__.py
endex_factset_ownership/types/factset_ownership/v1/__init__.py
endex_factset_ownership/types/factset_ownership/v1/fund_holding_create_params.py
endex_factset_ownership/types/factset_ownership/v1/fund_holding_list_params.py
endex_factset_ownership/types/factset_ownership/v1/fund_holdings_response.py
endex_factset_ownership/types/factset_ownership/v1/security_holder_create_params.py
endex_factset_ownership/types/factset_ownership/v1/security_holder_list_params.py
endex_factset_ownership-0.1.0a2.dist-info/METADATA
endex_factset_ownership-0.1.0a2.dist-info/WHEEL
endex_factset_ownership-0.1.0a2.dist-info/licenses/LICENSE
endex_factset_ownership-0.1.0a2.dist-info/RECORD
